odoo/addons/website_search_header/README.rst
odoo/addons/website_search_header/__init__.py
odoo/addons/website_search_header/__manifest__.py
odoo/addons/website_search_header/i18n/it.po
odoo/addons/website_search_header/i18n/website_search_header.pot
odoo/addons/website_search_header/readme/CONTRIBUTORS.md
odoo/addons/website_search_header/readme/DESCRIPTION.md
odoo/addons/website_search_header/readme/USAGE.md
odoo/addons/website_search_header/static/description/icon.png
odoo/addons/website_search_header/static/description/index.html
odoo/addons/website_search_header/static/src/js/website.js
odoo/addons/website_search_header/static/src/scss/website_search_header.scss
odoo/addons/website_search_header/views/templates.xml
odoo_addon_website_search_header-18.0.1.0.0.4.dist-info/METADATA
odoo_addon_website_search_header-18.0.1.0.0.4.dist-info/WHEEL
odoo_addon_website_search_header-18.0.1.0.0.4.dist-info/top_level.txt
odoo_addon_website_search_header-18.0.1.0.0.4.dist-info/RECORD
